setup.py
pylocate/__init__.py
pylocate/pylocate.py
pylocate.egg-info/PKG-INFO
pylocate.egg-info/SOURCES.txt
pylocate.egg-info/dependency_links.txt
pylocate.egg-info/entry_points.txt
pylocate.egg-info/top_level.txt
test/test_pylocate.py