Metadata-Version: 1.1
Name: pylocate
Version: 0.1.0
Summary: Simple locate script which also looks into zip archives
Home-page: http://github.com/ilovetux/pylocate
Author: iLoveTux
Author-email: me@ilovetux.com
License: GPLv3
Keywords: locate files zip
Platform: UNKNOWN
Classifier: Development Status :: 4 - Beta
Classifier: Topic :: Utilities
Classifier: License :: OSI Approved :: GNU General Public License v3 (GPLv3)
